{
  "resourceType": "ValueSet",
  "status": "draft",
  "name": "RecommendationJustificationClassifier",
  "id": "recommendation-justification-classifier",
  "title": "Recommendation Justification Classifier Codes Value Set",
  "description": "Codes for use with the Classifier drop-down menu for FEvIR(R): Recommendation Justification Builder.",
  "url": "https://hl7.org/fhir/uv/ebm/ValueSet/recommendation-justification-classifier",
  "experimental": false,
  "compose": {
    "include": [
      {
        "system": "https://fevir.net/resources/CodeSystem/27834"
      }
    ]
  }
}
