{"resourceType": "Group", "title": "OutcomeDefinition: HbA1c at 6 months", "status": "active", "meta": {"versionId": "3", "lastUpdated": "2023-11-23T22:30:54.614Z", "profile": ["https://hl7.org/fhir/uv/ebm/StructureDefinition/outcome-definition"]}, "url": "https://fevir.net/resources/Group/175762", "id": "175762", "publisher": "Computable Publishing LLC", "copyright": "https://creativecommons.org/licenses/by-nc-sa/4.0/", "contact": [{"telecom": [{"system": "email", "value": "support@computablepublishing.com"}]}], "extension": [{"url": "http://hl7.org/fhir/StructureDefinition/artifact-relatedArtifact", "valueRelatedArtifact": {"type": "cite-as", "citation": "OutcomeDefinition: HbA1c at 6 months [Group]. Contributors: Brian S. Alper [Authors/Creators]. In: Fast Evidence Interoperability Resources (FEvIR) Platform, FOI 175762. Revised 2023-11-09. Available at: https://fevir.net/resources/Group/175762. Computable resource at: https://fevir.net/resources/Group/175762."}}], "description": "HbA1c at 6 months", "membership": "conceptual", "characteristic": [{"description": "HbA1c at 6 months", "code": {"coding": [{"system": "http://hl7.org/fhir/fhir-types", "code": "Observation", "display": "Observation"}]}, "valueCodeableConcept": {"coding": [{"system": "http://loinc.org", "code": "4548-4", "display": "Hemoglobin A1c/Hemoglobin.total in Blood"}]}, "exclude": false, "timing": [{"contextCode": {"coding": [{"system": "http://snomed.info/sct", "code": "709491003", "display": "Enrollment in clinical trial"}]}, "offsetDuration": {"value": 6, "unit": "months", "system": "http://unitsofmeasure.org", "code": "mo"}, "text": "at 6 months"}]}], "identifier": [{"type": {"text": "FEvIR Object Identifier"}, "system": "https://fevir.net", "value": "175762", "assigner": {"display": "Computable Publishing LLC"}}], "author": [{"name": "Brian S. Alper"}], "useContext": [{"code": {"system": "https://fevir.net/resources/CodeSystem/179423", "version": "", "code": "evidence-communication", "display": "Evidence Communication"}, "valueCodeableConcept": {"coding": [{"system": "https://fevir.net/resources/CodeSystem/179423", "code": "OutcomeDefinition", "display": "OutcomeDefinition"}]}}], "type": "person"}